lib/Endpoint.py
lib/Fetch.py
lib/Parser.py
lib/__init__.py
sintak_unika_parser-1.0.0.dist-info/METADATA
sintak_unika_parser-1.0.0.dist-info/RECORD
sintak_unika_parser-1.0.0.dist-info/WHEEL
sintak_unika_parser-1.0.0.dist-info/top_level.txt
